Core_class.py
build_attr_schema_auto.py
constraint_kernel.py
dtype_utils.py
hybrid_constraint_engine-0.1.0.dist-info/METADATA
hybrid_constraint_engine-0.1.0.dist-info/WHEEL
hybrid_constraint_engine-0.1.0.dist-info/top_level.txt
hybrid_constraint_engine-0.1.0.dist-info/RECORD
