Metadata-Version: 2.4
Name: hybrid-constraint-engine
Version: 0.1.0
Summary: Constraint checking engine with vectorized NumPy + Numba (no-scale).
Author-email: Your Name <you@example.com>
License: Proprietary
Keywords: constraints,routing,numba,numpy
Classifier: Programming Language :: Python :: 3
Classifier: Programming Language :: Python :: 3 :: Only
Classifier: License :: Other/Proprietary License
Classifier: Operating System :: OS Independent
Requires-Python: >=3.9
Requires-Dist: numpy>=1.22
Requires-Dist: numba>=0.57
